plone.app.blocks-7.0.1-py3.11-nspkg.pth
plone/app/blocks/__init__.py
plone/app/blocks/configure.zcml
plone/app/blocks/drafting.py
plone/app/blocks/events.py
plone/app/blocks/indexing.py
plone/app/blocks/interfaces.py
plone/app/blocks/layoutbehavior.py
plone/app/blocks/layoutviews.py
plone/app/blocks/linkintegrity.py
plone/app/blocks/panel.py
plone/app/blocks/resource.py
plone/app/blocks/setuphandlers.py
plone/app/blocks/subscribers.py
plone/app/blocks/testing.py
plone/app/blocks/tiles.py
plone/app/blocks/transform.py
plone/app/blocks/utils.py
plone/app/blocks/profiles/default/browserlayer.xml
plone/app/blocks/profiles/default/metadata.xml
plone/app/blocks/profiles/default/plone.app.blocks_default.txt
plone/app/blocks/profiles/default/registry.xml
plone/app/blocks/profiles/default/rolemap.xml
plone/app/blocks/templates/main_template.pt
plone/app/blocks/tests/__init__.py
plone/app/blocks/tests/context.rst
plone/app/blocks/tests/esi.rst
plone/app/blocks/tests/rendering.rst
plone/app/blocks/tests/test_contentlayout.py
plone/app/blocks/tests/test_doctest.py
plone/app/blocks/tests/test_layoutbehavior.py
plone/app/blocks/tests/test_linkintegrity.py
plone/app/blocks/tests/test_page_sitelayout.py
plone/app/blocks/tests/test_resource.py
plone/app/blocks/tests/test_sitelayout.py
plone/app/blocks/tests/test_tiles.py
plone/app/blocks/tests/test_transforms.py
plone/app/blocks/tests/test_traversers.py
plone/app/blocks/tests/test_utils.py
plone/app/blocks/tests/resources/contentlayout/testlayout1/content.html
plone/app/blocks/tests/resources/contentlayout/testlayout2/manifest.cfg
plone/app/blocks/tests/resources/contentlayout/testlayout2/mylayout.html
plone/app/blocks/tests/resources/contentlayout/testlayout2/mylayout2.html
plone/app/blocks/tests/resources/sitelayout/testlayout1/site.html
plone/app/blocks/tests/resources/sitelayout/testlayout2/manifest.cfg
plone/app/blocks/tests/resources/sitelayout/testlayout2/mylayout.html
plone.app.blocks-7.0.1.dist-info/LICENSE.GPL
plone.app.blocks-7.0.1.dist-info/LICENSE.txt
plone.app.blocks-7.0.1.dist-info/METADATA
plone.app.blocks-7.0.1.dist-info/WHEEL
plone.app.blocks-7.0.1.dist-info/entry_points.txt
plone.app.blocks-7.0.1.dist-info/namespace_packages.txt
plone.app.blocks-7.0.1.dist-info/top_level.txt
plone.app.blocks-7.0.1.dist-info/RECORD
