Metadata-Version: 2.1
Name: plone.app.blocks
Version: 7.0.1
Summary: Implements the in-Plone blocks rendering process
Home-page: https://github.com/plone/plone.app.blocks
Author: Martin Aspeli, Laurence Rowe
Author-email: optilude@gmail.com
Maintainer: Plone Community
Maintainer-email: releaseteam@plone.org
License: GPLv2
Keywords: plone blocks deco
Classifier: Development Status :: 5 - Production/Stable
Classifier: Environment :: Web Environment
Classifier: Framework :: Plone
Classifier: Framework :: Plone :: Addon
Classifier: Framework :: Plone :: 6.0
Classifier: License :: OSI Approved :: GNU General Public License v2 (GPLv2)
Classifier: Programming Language :: Python
Classifier: Programming Language :: Python :: 3.8
Classifier: Programming Language :: Python :: 3.9
Classifier: Programming Language :: Python :: 3.10
Classifier: Programming Language :: Python :: 3.11
Classifier: Topic :: Internet :: WWW/HTTP
Classifier: Topic :: Internet :: WWW/HTTP :: Dynamic Content
Classifier: Topic :: Software Development :: Libraries :: Python Modules
Requires-Python: >=3.8
License-File: LICENSE.GPL
License-File: LICENSE.txt
Requires-Dist: lxml
Requires-Dist: plone.base
Requires-Dist: plone.jsonserializer
Requires-Dist: plone.subrequest
Requires-Dist: plone.tiles
Requires-Dist: repoze.xmliter
Requires-Dist: setuptools
Provides-Extra: test
Requires-Dist: plone.app.tiles ; extra == 'test'
Requires-Dist: plone.app.testing ; extra == 'test'
Requires-Dist: plone.testing ; extra == 'test'
